neatrl/__init__.py
neatrl/a2c.py
neatrl/ddpg.py
neatrl/dqn.py
neatrl/dueling_dqn.py
neatrl/ppo.py
neatrl/reinforce.py
neatrl/rnd.py
neatrl/sac.py
neatrl/td3.py
neatrl-1.0.0.dist-info/licenses/LICENSE
neatrl-1.0.0.dist-info/METADATA
neatrl-1.0.0.dist-info/WHEEL
neatrl-1.0.0.dist-info/top_level.txt
neatrl-1.0.0.dist-info/RECORD
