Metadata-Version: 2.4
Name: neatrl
Version: 1.0.0
Summary: A Python library for reinforcement learning algorithms
Author-email: Yuvraj Singh <yuvraj.mist@gmail.com>
License: MIT
Requires-Python: >=3.9
License-File: LICENSE
Requires-Dist: torch
Requires-Dist: numpy
Requires-Dist: gymnasium
Requires-Dist: stable-baselines3
Requires-Dist: tqdm
Requires-Dist: wandb
Requires-Dist: imageio[ffmpeg]
Requires-Dist: opencv-python
Requires-Dist: wandb[media]
Provides-Extra: mujoco
Requires-Dist: gymnasium[mujoco]; extra == "mujoco"
Provides-Extra: atari
Requires-Dist: gymnasium[atari]; extra == "atari"
Requires-Dist: ale-py; extra == "atari"
Provides-Extra: classic
Requires-Dist: gymnasium[classic-control]; extra == "classic"
Provides-Extra: box2d
Requires-Dist: swig; extra == "box2d"
Requires-Dist: gymnasium[box2d]; extra == "box2d"
Provides-Extra: dev
Requires-Dist: ruff; extra == "dev"
Requires-Dist: mypy; extra == "dev"
Requires-Dist: black; extra == "dev"
Requires-Dist: build; extra == "dev"
Requires-Dist: twine; extra == "dev"
Dynamic: license-file
